CHANGES.txt
LICENSE.txt
MANIFEST.in
README.txt
bootstrap.py
buildout.cfg
setup.py
eggs/backports.ssl_match_hostname-3.7.0.1-py3.10.egg/EGG-INFO/SOURCES.txt
eggs/backports.ssl_match_hostname-3.7.0.1-py3.10.egg/EGG-INFO/dependency_links.txt
eggs/backports.ssl_match_hostname-3.7.0.1-py3.10.egg/EGG-INFO/top_level.txt
eggs/cffi-1.17.1-py3.10-win-amd64.egg/EGG-INFO/entry_points.txt
eggs/cffi-1.17.1-py3.10-win-amd64.egg/EGG-INFO/requires.txt
eggs/cffi-1.17.1-py3.10-win-amd64.egg/EGG-INFO/top_level.txt
eggs/future-1.0.0-py3.10.egg/EGG-INFO/LICENSE.txt
eggs/future-1.0.0-py3.10.egg/EGG-INFO/entry_points.txt
eggs/future-1.0.0-py3.10.egg/EGG-INFO/top_level.txt
eggs/gevent-22.10.2-py3.10-win-amd64.egg/EGG-INFO/entry_points.txt
eggs/gevent-22.10.2-py3.10-win-amd64.egg/EGG-INFO/requires.txt
eggs/gevent-22.10.2-py3.10-win-amd64.egg/EGG-INFO/top_level.txt
eggs/gevent-22.10.2-py3.10-win-amd64.egg/gevent/tests/hosts_file.txt
eggs/gevent-22.10.2-py3.10-win-amd64.egg/gevent/tests/tests_that_dont_do_leakchecks.txt
eggs/gevent-22.10.2-py3.10-win-amd64.egg/gevent/tests/tests_that_dont_monkeypatch.txt
eggs/gevent-22.10.2-py3.10-win-amd64.egg/gevent/tests/tests_that_dont_use_resolver.txt
eggs/gevent-25.5.1-py3.10-win-amd64.egg/EGG-INFO/entry_points.txt
eggs/gevent-25.5.1-py3.10-win-amd64.egg/EGG-INFO/requires.txt
eggs/gevent-25.5.1-py3.10-win-amd64.egg/EGG-INFO/top_level.txt
eggs/gevent-25.5.1-py3.10-win-amd64.egg/gevent/tests/hosts_file.txt
eggs/gevent-25.5.1-py3.10-win-amd64.egg/gevent/tests/tests_that_dont_do_leakchecks.txt
eggs/gevent-25.5.1-py3.10-win-amd64.egg/gevent/tests/tests_that_dont_monkeypatch.txt
eggs/gevent-25.5.1-py3.10-win-amd64.egg/gevent/tests/tests_that_dont_use_resolver.txt
eggs/greenlet-3.2.3-py3.10-win-amd64.egg/EGG-INFO/requires.txt
eggs/greenlet-3.2.3-py3.10-win-amd64.egg/EGG-INFO/top_level.txt
eggs/ipaddress-1.0.23-py3.10.egg/EGG-INFO/LICENSE.txt
eggs/ipaddress-1.0.23-py3.10.egg/EGG-INFO/top_level.txt
eggs/lovely.recipe-1.0.0-py3.10.egg/EGG-INFO/SOURCES.txt
eggs/lovely.recipe-1.0.0-py3.10.egg/EGG-INFO/dependency_links.txt
eggs/lovely.recipe-1.0.0-py3.10.egg/EGG-INFO/entry_points.txt
eggs/lovely.recipe-1.0.0-py3.10.egg/EGG-INFO/namespace_packages.txt
eggs/lovely.recipe-1.0.0-py3.10.egg/EGG-INFO/requires.txt
eggs/lovely.recipe-1.0.0-py3.10.egg/EGG-INFO/top_level.txt
eggs/lovely.recipe-1.0.0-py3.10.egg/lovely/recipe/egg/README.txt
eggs/lovely.recipe-1.0.0-py3.10.egg/lovely/recipe/fs/README.txt
eggs/lovely.recipe-1.0.0-py3.10.egg/lovely/recipe/fs/mkdir-root.txt
eggs/lovely.recipe-1.0.0-py3.10.egg/lovely/recipe/i18n/README.txt
eggs/lovely.recipe-1.0.0-py3.10.egg/lovely/recipe/importchecker/README.txt
eggs/lxml-6.0.0-py3.10-win-amd64.egg/EGG-INFO/requires.txt
eggs/lxml-6.0.0-py3.10-win-amd64.egg/EGG-INFO/top_level.txt
eggs/lxml-6.0.0-py3.10-win-amd64.egg/EGG-INFO/licenses/LICENSE.txt
eggs/lxml-6.0.0-py3.10-win-amd64.egg/EGG-INFO/licenses/LICENSES.txt
eggs/lxml-6.0.0-py3.10-win-amd64.egg/lxml/isoschematron/resources/xsl/iso-schematron-xslt1/readme.txt
eggs/p01.checker-0.5.9-py3.10.egg/EGG-INFO/SOURCES.txt
eggs/p01.checker-0.5.9-py3.10.egg/EGG-INFO/dependency_links.txt
eggs/p01.checker-0.5.9-py3.10.egg/EGG-INFO/namespace_packages.txt
eggs/p01.checker-0.5.9-py3.10.egg/EGG-INFO/requires.txt
eggs/p01.checker-0.5.9-py3.10.egg/EGG-INFO/top_level.txt
eggs/p01.checker-0.5.9-py3.10.egg/p01/checker/checker.txt
eggs/p01.checker-0.5.9-py3.10.egg/p01/checker/sample/tab.txt
eggs/polib-1.2.0-py3.10.egg/EGG-INFO/top_level.txt
eggs/pycparser-2.22-py3.10.egg/EGG-INFO/top_level.txt
eggs/pyflakes-3.4.0-py3.10.egg/EGG-INFO/entry_points.txt
eggs/pyflakes-3.4.0-py3.10.egg/EGG-INFO/top_level.txt
eggs/zc.recipe.egg-2.0.7-py3.10.egg/EGG-INFO/SOURCES.txt
eggs/zc.recipe.egg-2.0.7-py3.10.egg/EGG-INFO/dependency_links.txt
eggs/zc.recipe.egg-2.0.7-py3.10.egg/EGG-INFO/entry_points.txt
eggs/zc.recipe.egg-2.0.7-py3.10.egg/EGG-INFO/namespace_packages.txt
eggs/zc.recipe.egg-2.0.7-py3.10.egg/EGG-INFO/requires.txt
eggs/zc.recipe.egg-2.0.7-py3.10.egg/EGG-INFO/top_level.txt
eggs/zc.recipe.testrunner-3.2-py3.10.egg/EGG-INFO/LICENSE.txt
eggs/zc.recipe.testrunner-3.2-py3.10.egg/EGG-INFO/entry_points.txt
eggs/zc.recipe.testrunner-3.2-py3.10.egg/EGG-INFO/namespace_packages.txt
eggs/zc.recipe.testrunner-3.2-py3.10.egg/EGG-INFO/requires.txt
eggs/zc.recipe.testrunner-3.2-py3.10.egg/EGG-INFO/top_level.txt
eggs/zope.event-5.0-py3.10.egg/EGG-INFO/LICENSE.txt
eggs/zope.event-5.0-py3.10.egg/EGG-INFO/namespace_packages.txt
eggs/zope.event-5.0-py3.10.egg/EGG-INFO/requires.txt
eggs/zope.event-5.0-py3.10.egg/EGG-INFO/top_level.txt
eggs/zope.exceptions-5.2-py3.10.egg/EGG-INFO/LICENSE.txt
eggs/zope.exceptions-5.2-py3.10.egg/EGG-INFO/namespace_packages.txt
eggs/zope.exceptions-5.2-py3.10.egg/EGG-INFO/requires.txt
eggs/zope.exceptions-5.2-py3.10.egg/EGG-INFO/top_level.txt
eggs/zope.interface-7.2-py3.10-win-amd64.egg/EGG-INFO/LICENSE.txt
eggs/zope.interface-7.2-py3.10-win-amd64.egg/EGG-INFO/namespace_packages.txt
eggs/zope.interface-7.2-py3.10-win-amd64.egg/EGG-INFO/requires.txt
eggs/zope.interface-7.2-py3.10-win-amd64.egg/EGG-INFO/top_level.txt
eggs/zope.testrunner-7.4-py3.10.egg/EGG-INFO/entry_points.txt
eggs/zope.testrunner-7.4-py3.10.egg/EGG-INFO/namespace_packages.txt
eggs/zope.testrunner-7.4-py3.10.egg/EGG-INFO/requires.txt
eggs/zope.testrunner-7.4-py3.10.egg/EGG-INFO/top_level.txt
src/p01/__init__.py
src/p01.env.egg-info/PKG-INFO
src/p01.env.egg-info/SOURCES.txt
src/p01.env.egg-info/dependency_links.txt
src/p01.env.egg-info/namespace_packages.txt
src/p01.env.egg-info/not-zip-safe
src/p01.env.egg-info/requires.txt
src/p01.env.egg-info/top_level.txt
src/p01/env/README.txt
src/p01/env/__init__.py
src/p01/env/env.py
src/p01/env/bugfix/__init__.py
src/p01/env/bugfix/ssl_match_hostname.py
src/p01/env/tests/__init__.py
src/p01/env/tests/bugfix-ssl.txt
src/p01/env/tests/checker.txt
src/p01/env/tests/tests.py