Metadata-Version: 2.1
Name: p01.env
Version: 0.5.2
Summary: Helper methods for setup a production server environment
Home-page: http://pypi.python.org/pypi/p01.env
Author: Roger Ineichen, Projekt01 GmbH
Author-email: dev@projekt01.ch
License: ZPL 2.1
Keywords: p01 bootstrap setup Zope3
Platform: UNKNOWN
Classifier: Development Status :: 5 - Production/Stable
Classifier: Environment :: Web Environment
Classifier: Intended Audience :: Developers
Classifier: License :: OSI Approved :: Zope Public License
Classifier: Programming Language :: Python
Classifier: Natural Language :: English
Classifier: Operating System :: OS Independent
Classifier: Topic :: Internet :: WWW/HTTP
Classifier: Framework :: Zope3
Provides-Extra: test
Provides-Extra: ssl
Provides-Extra: gevent
